plantlabeller/__init__.py
plantlabeller/calculator.py
plantlabeller/tkinterGUI.py
plantlabeller/tkintercore.py
plantlabeller-0.2.9.dist-info/METADATA
plantlabeller-0.2.9.dist-info/WHEEL
plantlabeller-0.2.9.dist-info/top_level.txt
plantlabeller-0.2.9.dist-info/RECORD
